domain_finder_r/__init__.py
domain_finder_r/a.py
domain_finder_r/o.py
domain_finder_r/trial.py
domain_finder_r/dnsdumpster/API_example.py
domain_finder_r/dnsdumpster/DNSDumpsterAPI.py
domain_finder_r/dnsdumpster/__init__.py
domain_finder_r/dnsdumpster/test_api.py
domain_finder_r-0.0.4.dist-info/LICENSE
domain_finder_r-0.0.4.dist-info/METADATA
domain_finder_r-0.0.4.dist-info/WHEEL
domain_finder_r-0.0.4.dist-info/top_level.txt
domain_finder_r-0.0.4.dist-info/RECORD
